{
  "entry": [
    {"node": "repeat_start", "flag": "met_merchant"},
    {"node": "start"}
  ],
  "start": {
    "text": "Привет, путник. Давно тебя не видели в этих краях. Надеюсь с тобой всё в порядке?",
    "set_flag": "met_merchant",
    "options": [
      {"text": "Кто ты?", "next": "who_are_you"},
      {"text": "Расскажи о городе", "next": "about_city"},
      {"text": "Пока", "next": null}
    ]
  },
  "repeat_start": {
    "text": "А, я тебя помню! Снова заглянул? Чем могу помочь?",
    "options": [
      {"text": "Что продаёшь?", "next": "shop"},
      {"text": "Расскажи о городе", "next": "about_city"},
      {"text": "Да так, мимо проходил. Пока", "next": null}
    ]
  },
  "who_are_you": {
    "text": "Я местный торговец. Тут уже лет двадцать.",
    "options": [
      {"text": "Что продаёшь?", "next": "shop"},
      {"text": "Ладно, пока", "next": null}
    ]
  },
  "about_city": {
    "text": "Город основан сто лет назад. Раньше тут было тихое поселение, а теперь — целый торговый узел.",
    "options": [
      {"text": "Интересно. А ты кто?", "next": "who_are_you"},
      {"text": "Спасибо, пока", "next": null}
    ]
  },
  "shop": {
    "text": "Всякое барахло — зелья, свитки, старые карты. Заходи, если что понадобится.",
    "options": [
      {"text": "Спасибо, загляну", "next": null},
      {"text": "А что ещё расскажешь?", "next": "repeat_start"}
    ]
  }
}
